{
    "street_name_ADMIRALTY LINK": 0,
    "street_name_AH HOOD RD": 1,
    "street_name_ALEXANDRA RD": 2,
    "street_name_ALJUNIED AVE 2": 3,
    "street_name_ALJUNIED CRES": 4,
    "street_name_ALJUNIED RD": 5,
    "street_name_ALKAFF CRES": 6,
    "street_name_ANCHORVALE CRES": 7,
    "street_name_ANCHORVALE DR": 8,
    "street_name_ANCHORVALE LANE": 9,
    "street_name_ANCHORVALE LINK": 10,
    "street_name_ANCHORVALE RD": 11,
    "street_name_ANCHORVALE ST": 12,
    "street_name_ANG MO KIO AVE 1": 13,
    "street_name_ANG MO KIO AVE 10": 14,
    "street_name_ANG MO KIO AVE 2": 15,
    "street_name_ANG MO KIO AVE 3": 16,
    "street_name_ANG MO KIO AVE 4": 17,
    "street_name_ANG MO KIO AVE 5": 18,
    "street_name_ANG MO KIO AVE 6": 19,
    "street_name_ANG MO KIO AVE 8": 20,
    "street_name_ANG MO KIO AVE 9": 21,
    "street_name_ANG MO KIO ST 11": 22,
    "street_name_ANG MO KIO ST 21": 23,
    "street_name_ANG MO KIO ST 31": 24,
    "street_name_ANG MO KIO ST 32": 25,
    "street_name_ANG MO KIO ST 44": 26,
    "street_name_ANG MO KIO ST 51": 27,
    "street_name_ANG MO KIO ST 52": 28,
    "street_name_ANG MO KIO ST 61": 29,
    "street_name_BAIN ST": 30,
    "street_name_BALAM RD": 31,
    "street_name_BANGKIT RD": 32,
    "street_name_BEACH RD": 33,
    "street_name_BEDOK CTRL": 34,
    "street_name_BEDOK NTH AVE 1": 35,
    "street_name_BEDOK NTH AVE 2": 36,
    "street_name_BEDOK NTH AVE 3": 37,
    "street_name_BEDOK NTH AVE 4": 38,
    "street_name_BEDOK NTH RD": 39,
    "street_name_BEDOK NTH ST 1": 40,
    "street_name_BEDOK NTH ST 2": 41,
    "street_name_BEDOK NTH ST 3": 42,
    "street_name_BEDOK NTH ST 4": 43,
    "street_name_BEDOK RESERVOIR CRES": 44,
    "street_name_BEDOK RESERVOIR RD": 45,
    "street_name_BEDOK RESERVOIR VIEW": 46,
    "street_name_BEDOK STH AVE 1": 47,
    "street_name_BEDOK STH AVE 2": 48,
    "street_name_BEDOK STH AVE 3": 49,
    "street_name_BEDOK STH RD": 50,
    "street_name_BENDEMEER RD": 51,
    "street_name_BEO CRES": 52,
    "street_name_BIDADARI PK DR": 53,
    "street_name_BISHAN ST 11": 54,
    "street_name_BISHAN ST 12": 55,
    "street_name_BISHAN ST 13": 56,
    "street_name_BISHAN ST 22": 57,
    "street_name_BISHAN ST 23": 58,
    "street_name_BISHAN ST 24": 59,
    "street_name_BOON KENG RD": 60,
    "street_name_BOON LAY AVE": 61,
    "street_name_BOON LAY DR": 62,
    "street_name_BOON LAY PL": 63,
    "street_name_BOON TIONG RD": 64,
    "street_name_BRIGHT HILL DR": 65,
    "street_name_BT BATOK CTRL": 66,
    "street_name_BT BATOK EAST AVE 3": 67,
    "street_name_BT BATOK EAST AVE 4": 68,
    "street_name_BT BATOK EAST AVE 5": 69,
    "street_name_BT BATOK EAST AVE 6": 70,
    "street_name_BT BATOK ST 11": 71,
    "street_name_BT BATOK ST 21": 72,
    "street_name_BT BATOK ST 22": 73,
    "street_name_BT BATOK ST 24": 74,
    "street_name_BT BATOK ST 25": 75,
    "street_name_BT BATOK ST 31": 76,
    "street_name_BT BATOK ST 32": 77,
    "street_name_BT BATOK ST 33": 78,
    "street_name_BT BATOK ST 34": 79,
    "street_name_BT BATOK ST 51": 80,
    "street_name_BT BATOK ST 52": 81,
    "street_name_BT BATOK WEST AVE 2": 82,
    "street_name_BT BATOK WEST AVE 4": 83,
    "street_name_BT BATOK WEST AVE 5": 84,
    "street_name_BT BATOK WEST AVE 6": 85,
    "street_name_BT BATOK WEST AVE 7": 86,
    "street_name_BT BATOK WEST AVE 8": 87,
    "street_name_BT BATOK WEST AVE 9": 88,
    "street_name_BT MERAH CTRL": 89,
    "street_name_BT MERAH LANE 1": 90,
    "street_name_BT MERAH VIEW": 91,
    "street_name_BT PANJANG RING RD": 92,
    "street_name_BT PURMEI RD": 93,
    "street_name_BUANGKOK CRES": 94,
    "street_name_BUANGKOK GREEN": 95,
    "street_name_BUANGKOK LINK": 96,
    "street_name_BUANGKOK STH FARMWAY 1": 97,
    "street_name_BUFFALO RD": 98,
    "street_name_C'WEALTH AVE": 99,
    "street_name_C'WEALTH AVE WEST": 100,
    "street_name_C'WEALTH CL": 101,
    "street_name_C'WEALTH CRES": 102,
    "street_name_C'WEALTH DR": 103,
    "street_name_CAMBRIDGE RD": 104,
    "street_name_CANBERRA CRES": 105,
    "street_name_CANBERRA LINK": 106,
    "street_name_CANBERRA RD": 107,
    "street_name_CANBERRA ST": 108,
    "street_name_CANBERRA VIEW": 109,
    "street_name_CANBERRA WALK": 110,
    "street_name_CANTONMENT CL": 111,
    "street_name_CANTONMENT RD": 112,
    "street_name_CASHEW RD": 113,
    "street_name_CASSIA CRES": 114,
    "street_name_CHAI CHEE AVE": 115,
    "street_name_CHAI CHEE DR": 116,
    "street_name_CHAI CHEE RD": 117,
    "street_name_CHAI CHEE ST": 118,
    "street_name_CHANDER RD": 119,
    "street_name_CHANGI VILLAGE RD": 120,
    "street_name_CHIN SWEE RD": 121,
    "street_name_CHOA CHU KANG AVE 1": 122,
    "street_name_CHOA CHU KANG AVE 2": 123,
    "street_name_CHOA CHU KANG AVE 3": 124,
    "street_name_CHOA CHU KANG AVE 4": 125,
    "street_name_CHOA CHU KANG AVE 5": 126,
    "street_name_CHOA CHU KANG AVE 7": 127,
    "street_name_CHOA CHU KANG CRES": 128,
    "street_name_CHOA CHU KANG CTRL": 129,
    "street_name_CHOA CHU KANG DR": 130,
    "street_name_CHOA CHU KANG LOOP": 131,
    "street_name_CHOA CHU KANG NTH 5": 132,
    "street_name_CHOA CHU KANG NTH 6": 133,
    "street_name_CHOA CHU KANG NTH 7": 134,
    "street_name_CHOA CHU KANG ST 51": 135,
    "street_name_CHOA CHU KANG ST 52": 136,
    "street_name_CHOA CHU KANG ST 53": 137,
    "street_name_CHOA CHU KANG ST 54": 138,
    "street_name_CHOA CHU KANG ST 62": 139,
    "street_name_CHOA CHU KANG ST 64": 140,
    "street_name_CIRCUIT RD": 141,
    "street_name_CLARENCE LANE": 142,
    "street_name_CLEMENTI AVE 1": 143,
    "street_name_CLEMENTI AVE 2": 144,
    "street_name_CLEMENTI AVE 3": 145,
    "street_name_CLEMENTI AVE 4": 146,
    "street_name_CLEMENTI AVE 5": 147,
    "street_name_CLEMENTI AVE 6": 148,
    "street_name_CLEMENTI ST 11": 149,
    "street_name_CLEMENTI ST 12": 150,
    "street_name_CLEMENTI ST 13": 151,
    "street_name_CLEMENTI ST 14": 152,
    "street_name_CLEMENTI WEST ST 1": 153,
    "street_name_CLEMENTI WEST ST 2": 154,
    "street_name_COMPASSVALE BOW": 155,
    "street_name_COMPASSVALE CRES": 156,
    "street_name_COMPASSVALE DR": 157,
    "street_name_COMPASSVALE LANE": 158,
    "street_name_COMPASSVALE LINK": 159,
    "street_name_COMPASSVALE RD": 160,
    "street_name_COMPASSVALE ST": 161,
    "street_name_COMPASSVALE WALK": 162,
    "street_name_CORPORATION DR": 163,
    "street_name_CRAWFORD LANE": 164,
    "street_name_DAKOTA CRES": 165,
    "street_name_DAWSON RD": 166,
    "street_name_DELTA AVE": 167,
    "street_name_DEPOT RD": 168,
    "street_name_DORSET RD": 169,
    "street_name_DOVER CL EAST": 170,
    "street_name_DOVER CRES": 171,
    "street_name_DOVER RD": 172,
    "street_name_EAST COAST RD": 173,
    "street_name_EDGEDALE PLAINS": 174,
    "street_name_EDGEFIELD PLAINS": 175,
    "street_name_ELIAS RD": 176,
    "street_name_EMPRESS RD": 177,
    "street_name_EUNOS CRES": 178,
    "street_name_EUNOS RD 5": 179,
    "street_name_EVERTON PK": 180,
    "street_name_FAJAR RD": 181,
    "street_name_FARRER PK RD": 182,
    "street_name_FARRER RD": 183,
    "street_name_FERNVALE LANE": 184,
    "street_name_FERNVALE LINK": 185,
    "street_name_FERNVALE RD": 186,
    "street_name_FERNVALE ST": 187,
    "street_name_FRENCH RD": 188,
    "street_name_GANGSA RD": 189,
    "street_name_GEYLANG BAHRU": 190,
    "street_name_GEYLANG EAST AVE 1": 191,
    "street_name_GEYLANG EAST AVE 2": 192,
    "street_name_GEYLANG EAST CTRL": 193,
    "street_name_GEYLANG SERAI": 194,
    "street_name_GHIM MOH LINK": 195,
    "street_name_GHIM MOH RD": 196,
    "street_name_GLOUCESTER RD": 197,
    "street_name_HAIG RD": 198,
    "street_name_HAVELOCK RD": 199,
    "street_name_HENDERSON CRES": 200,
    "street_name_HENDERSON RD": 201,
    "street_name_HILLVIEW AVE": 202,
    "street_name_HO CHING RD": 203,
    "street_name_HOLLAND AVE": 204,
    "street_name_HOLLAND CL": 205,
    "street_name_HOLLAND DR": 206,
    "street_name_HOUGANG AVE 1": 207,
    "street_name_HOUGANG AVE 10": 208,
    "street_name_HOUGANG AVE 2": 209,
    "street_name_HOUGANG AVE 3": 210,
    "street_name_HOUGANG AVE 4": 211,
    "street_name_HOUGANG AVE 5": 212,
    "street_name_HOUGANG AVE 6": 213,
    "street_name_HOUGANG AVE 7": 214,
    "street_name_HOUGANG AVE 8": 215,
    "street_name_HOUGANG AVE 9": 216,
    "street_name_HOUGANG CTRL": 217,
    "street_name_HOUGANG ST 11": 218,
    "street_name_HOUGANG ST 21": 219,
    "street_name_HOUGANG ST 22": 220,
    "street_name_HOUGANG ST 31": 221,
    "street_name_HOUGANG ST 32": 222,
    "street_name_HOUGANG ST 51": 223,
    "street_name_HOUGANG ST 52": 224,
    "street_name_HOUGANG ST 61": 225,
    "street_name_HOUGANG ST 91": 226,
    "street_name_HOUGANG ST 92": 227,
    "street_name_HOY FATT RD": 228,
    "street_name_HU CHING RD": 229,
    "street_name_INDUS RD": 230,
    "street_name_JELAPANG RD": 231,
    "street_name_JELEBU RD": 232,
    "street_name_JELLICOE RD": 233,
    "street_name_JLN BAHAGIA": 234,
    "street_name_JLN BATU": 235,
    "street_name_JLN BERSEH": 236,
    "street_name_JLN BT HO SWEE": 237,
    "street_name_JLN BT MERAH": 238,
    "street_name_JLN DAMAI": 239,
    "street_name_JLN DUA": 240,
    "street_name_JLN DUSUN": 241,
    "street_name_JLN KAYU": 242,
    "street_name_JLN KLINIK": 243,
    "street_name_JLN KUKOH": 244,
    "street_name_JLN MA'MOR": 245,
    "street_name_JLN MEMBINA": 246,
    "street_name_JLN MEMBINA BARAT": 247,
    "street_name_JLN PASAR BARU": 248,
    "street_name_JLN RAJAH": 249,
    "street_name_JLN RUMAH TINGGI": 250,
    "street_name_JLN TECK WHYE": 251,
    "street_name_JLN TENAGA": 252,
    "street_name_JLN TENTERAM": 253,
    "street_name_JLN TIGA": 254,
    "street_name_JOO CHIAT RD": 255,
    "street_name_JOO SENG RD": 256,
    "street_name_JURONG EAST AVE 1": 257,
    "street_name_JURONG EAST ST 13": 258,
    "street_name_JURONG EAST ST 21": 259,
    "street_name_JURONG EAST ST 24": 260,
    "street_name_JURONG EAST ST 31": 261,
    "street_name_JURONG EAST ST 32": 262,
    "street_name_JURONG WEST AVE 1": 263,
    "street_name_JURONG WEST AVE 3": 264,
    "street_name_JURONG WEST AVE 5": 265,
    "street_name_JURONG WEST CTRL 1": 266,
    "street_name_JURONG WEST CTRL 3": 267,
    "street_name_JURONG WEST ST 24": 268,
    "street_name_JURONG WEST ST 25": 269,
    "street_name_JURONG WEST ST 41": 270,
    "street_name_JURONG WEST ST 42": 271,
    "street_name_JURONG WEST ST 51": 272,
    "street_name_JURONG WEST ST 52": 273,
    "street_name_JURONG WEST ST 61": 274,
    "street_name_JURONG WEST ST 62": 275,
    "street_name_JURONG WEST ST 64": 276,
    "street_name_JURONG WEST ST 65": 277,
    "street_name_JURONG WEST ST 71": 278,
    "street_name_JURONG WEST ST 72": 279,
    "street_name_JURONG WEST ST 73": 280,
    "street_name_JURONG WEST ST 74": 281,
    "street_name_JURONG WEST ST 75": 282,
    "street_name_JURONG WEST ST 81": 283,
    "street_name_JURONG WEST ST 91": 284,
    "street_name_JURONG WEST ST 92": 285,
    "street_name_JURONG WEST ST 93": 286,
    "street_name_KALLANG BAHRU": 287,
    "street_name_KANG CHING RD": 288,
    "street_name_KEAT HONG CL": 289,
    "street_name_KEAT HONG LINK": 290,
    "street_name_KELANTAN RD": 291,
    "street_name_KENT RD": 292,
    "street_name_KG ARANG RD": 293,
    "street_name_KG BAHRU HILL": 294,
    "street_name_KG KAYU RD": 295,
    "street_name_KIM CHENG ST": 296,
    "street_name_KIM KEAT AVE": 297,
    "street_name_KIM KEAT LINK": 298,
    "street_name_KIM PONG RD": 299,
    "street_name_KIM TIAN PL": 300,
    "street_name_KIM TIAN RD": 301,
    "street_name_KING GEORGE'S AVE": 302,
    "street_name_KLANG LANE": 303,
    "street_name_KRETA AYER RD": 304,
    "street_name_LENGKOK BAHRU": 305,
    "street_name_LENGKONG TIGA": 306,
    "street_name_LIM CHU KANG RD": 307,
    "street_name_LIM LIAK ST": 308,
    "street_name_LOMPANG RD": 309,
    "street_name_LOR 1 TOA PAYOH": 310,
    "street_name_LOR 1A TOA PAYOH": 311,
    "street_name_LOR 2 TOA PAYOH": 312,
    "street_name_LOR 3 GEYLANG": 313,
    "street_name_LOR 3 TOA PAYOH": 314,
    "street_name_LOR 4 TOA PAYOH": 315,
    "street_name_LOR 5 TOA PAYOH": 316,
    "street_name_LOR 6 TOA PAYOH": 317,
    "street_name_LOR 7 TOA PAYOH": 318,
    "street_name_LOR 8 TOA PAYOH": 319,
    "street_name_LOR AH SOO": 320,
    "street_name_LOR LEW LIAN": 321,
    "street_name_LOR LIMAU": 322,
    "street_name_LOWER DELTA RD": 323,
    "street_name_MACPHERSON LANE": 324,
    "street_name_MARGARET DR": 325,
    "street_name_MARINE CRES": 326,
    "street_name_MARINE DR": 327,
    "street_name_MARINE PARADE CTRL": 328,
    "street_name_MARINE TER": 329,
    "street_name_MARSILING CRES": 330,
    "street_name_MARSILING DR": 331,
    "street_name_MARSILING LANE": 332,
    "street_name_MARSILING RD": 333,
    "street_name_MARSILING RISE": 334,
    "street_name_MCNAIR RD": 335,
    "street_name_MEI LING ST": 336,
    "street_name_MOH GUAN TER": 337,
    "street_name_MONTREAL DR": 338,
    "street_name_MONTREAL LINK": 339,
    "street_name_MOULMEIN RD": 340,
    "street_name_NEW MKT RD": 341,
    "street_name_NEW UPP CHANGI RD": 342,
    "street_name_NILE RD": 343,
    "street_name_NTH BRIDGE RD": 344,
    "street_name_OLD AIRPORT RD": 345,
    "street_name_OUTRAM HILL": 346,
    "street_name_OUTRAM PK": 347,
    "street_name_OWEN RD": 348,
    "street_name_PANDAN GDNS": 349,
    "street_name_PASIR RIS DR 1": 350,
    "street_name_PASIR RIS DR 10": 351,
    "street_name_PASIR RIS DR 3": 352,
    "street_name_PASIR RIS DR 4": 353,
    "street_name_PASIR RIS DR 6": 354,
    "street_name_PASIR RIS ST 11": 355,
    "street_name_PASIR RIS ST 12": 356,
    "street_name_PASIR RIS ST 13": 357,
    "street_name_PASIR RIS ST 21": 358,
    "street_name_PASIR RIS ST 41": 359,
    "street_name_PASIR RIS ST 51": 360,
    "street_name_PASIR RIS ST 52": 361,
    "street_name_PASIR RIS ST 53": 362,
    "street_name_PASIR RIS ST 71": 363,
    "street_name_PASIR RIS ST 72": 364,
    "street_name_PAYA LEBAR WAY": 365,
    "street_name_PENDING RD": 366,
    "street_name_PETIR RD": 367,
    "street_name_PINE CL": 368,
    "street_name_PIPIT RD": 369,
    "street_name_POTONG PASIR AVE 1": 370,
    "street_name_POTONG PASIR AVE 2": 371,
    "street_name_POTONG PASIR AVE 3": 372,
    "street_name_PUNGGOL CTRL": 373,
    "street_name_PUNGGOL DR": 374,
    "street_name_PUNGGOL EAST": 375,
    "street_name_PUNGGOL FIELD": 376,
    "street_name_PUNGGOL FIELD WALK": 377,
    "street_name_PUNGGOL PL": 378,
    "street_name_PUNGGOL RD": 379,
    "street_name_PUNGGOL WALK": 380,
    "street_name_PUNGGOL WAY": 381,
    "street_name_QUEEN ST": 382,
    "street_name_QUEEN'S CL": 383,
    "street_name_QUEEN'S RD": 384,
    "street_name_QUEENSWAY": 385,
    "street_name_RACE COURSE RD": 386,
    "street_name_REDHILL CL": 387,
    "street_name_REDHILL LANE": 388,
    "street_name_REDHILL RD": 389,
    "street_name_RIVERVALE CRES": 390,
    "street_name_RIVERVALE DR": 391,
    "street_name_RIVERVALE ST": 392,
    "street_name_RIVERVALE WALK": 393,
    "street_name_ROCHOR RD": 394,
    "street_name_ROWELL RD": 395,
    "street_name_SAGO LANE": 396,
    "street_name_SAUJANA RD": 397,
    "street_name_SEGAR RD": 398,
    "street_name_SELEGIE RD": 399,
    "street_name_SELETAR WEST FARMWAY 6": 400,
    "street_name_SEMBAWANG CL": 401,
    "street_name_SEMBAWANG CRES": 402,
    "street_name_SEMBAWANG DR": 403,
    "street_name_SEMBAWANG RD": 404,
    "street_name_SEMBAWANG VISTA": 405,
    "street_name_SEMBAWANG WAY": 406,
    "street_name_SENG POH RD": 407,
    "street_name_SENGKANG CTRL": 408,
    "street_name_SENGKANG EAST AVE": 409,
    "street_name_SENGKANG EAST RD": 410,
    "street_name_SENGKANG EAST WAY": 411,
    "street_name_SENGKANG WEST AVE": 412,
    "street_name_SENGKANG WEST RD": 413,
    "street_name_SENGKANG WEST WAY": 414,
    "street_name_SENJA LINK": 415,
    "street_name_SENJA RD": 416,
    "street_name_SERANGOON AVE 1": 417,
    "street_name_SERANGOON AVE 2": 418,
    "street_name_SERANGOON AVE 3": 419,
    "street_name_SERANGOON AVE 4": 420,
    "street_name_SERANGOON CTRL": 421,
    "street_name_SERANGOON CTRL DR": 422,
    "street_name_SERANGOON NTH AVE 1": 423,
    "street_name_SERANGOON NTH AVE 2": 424,
    "street_name_SERANGOON NTH AVE 3": 425,
    "street_name_SERANGOON NTH AVE 4": 426,
    "street_name_SHORT ST": 427,
    "street_name_SHUNFU RD": 428,
    "street_name_SILAT AVE": 429,
    "street_name_SIMEI LANE": 430,
    "street_name_SIMEI RD": 431,
    "street_name_SIMEI ST 1": 432,
    "street_name_SIMEI ST 2": 433,
    "street_name_SIMEI ST 4": 434,
    "street_name_SIMEI ST 5": 435,
    "street_name_SIMS AVE": 436,
    "street_name_SIMS DR": 437,
    "street_name_SIMS PL": 438,
    "street_name_SIN MING AVE": 439,
    "street_name_SIN MING RD": 440,
    "street_name_SMITH ST": 441,
    "street_name_SPOTTISWOODE PK RD": 442,
    "street_name_ST. GEORGE'S LANE": 443,
    "street_name_ST. GEORGE'S RD": 444,
    "street_name_STIRLING RD": 445,
    "street_name_STRATHMORE AVE": 446,
    "street_name_SUMANG LANE": 447,
    "street_name_SUMANG LINK": 448,
    "street_name_SUMANG WALK": 449,
    "street_name_TAH CHING RD": 450,
    "street_name_TAMAN HO SWEE": 451,
    "street_name_TAMPINES AVE 1": 452,
    "street_name_TAMPINES AVE 4": 453,
    "street_name_TAMPINES AVE 5": 454,
    "street_name_TAMPINES AVE 7": 455,
    "street_name_TAMPINES AVE 8": 456,
    "street_name_TAMPINES AVE 9": 457,
    "street_name_TAMPINES CTRL 1": 458,
    "street_name_TAMPINES CTRL 7": 459,
    "street_name_TAMPINES CTRL 8": 460,
    "street_name_TAMPINES NTH DR 1": 461,
    "street_name_TAMPINES ST 11": 462,
    "street_name_TAMPINES ST 12": 463,
    "street_name_TAMPINES ST 21": 464,
    "street_name_TAMPINES ST 22": 465,
    "street_name_TAMPINES ST 23": 466,
    "street_name_TAMPINES ST 24": 467,
    "street_name_TAMPINES ST 32": 468,
    "street_name_TAMPINES ST 33": 469,
    "street_name_TAMPINES ST 34": 470,
    "street_name_TAMPINES ST 41": 471,
    "street_name_TAMPINES ST 42": 472,
    "street_name_TAMPINES ST 43": 473,
    "street_name_TAMPINES ST 44": 474,
    "street_name_TAMPINES ST 45": 475,
    "street_name_TAMPINES ST 61": 476,
    "street_name_TAMPINES ST 71": 477,
    "street_name_TAMPINES ST 72": 478,
    "street_name_TAMPINES ST 81": 479,
    "street_name_TAMPINES ST 82": 480,
    "street_name_TAMPINES ST 83": 481,
    "street_name_TAMPINES ST 84": 482,
    "street_name_TAMPINES ST 86": 483,
    "street_name_TAMPINES ST 91": 484,
    "street_name_TANGLIN HALT RD": 485,
    "street_name_TAO CHING RD": 486,
    "street_name_TEBAN GDNS RD": 487,
    "street_name_TECK WHYE AVE": 488,
    "street_name_TECK WHYE CRES": 489,
    "street_name_TECK WHYE LANE": 490,
    "street_name_TELOK BLANGAH CRES": 491,
    "street_name_TELOK BLANGAH DR": 492,
    "street_name_TELOK BLANGAH HTS": 493,
    "street_name_TELOK BLANGAH RISE": 494,
    "street_name_TELOK BLANGAH ST 31": 495,
    "street_name_TELOK BLANGAH WAY": 496,
    "street_name_TESSENSOHN RD": 497,
    "street_name_TG PAGAR PLAZA": 498,
    "street_name_TIONG BAHRU RD": 499,
    "street_name_TOA PAYOH CTRL": 500,
    "street_name_TOA PAYOH EAST": 501,
    "street_name_TOA PAYOH NTH": 502,
    "street_name_TOH GUAN RD": 503,
    "street_name_TOH YI DR": 504,
    "street_name_TOWNER RD": 505,
    "street_name_UBI AVE 1": 506,
    "street_name_UPP ALJUNIED LANE": 507,
    "street_name_UPP BOON KENG RD": 508,
    "street_name_UPP CROSS ST": 509,
    "street_name_UPP SERANGOON CRES": 510,
    "street_name_UPP SERANGOON RD": 511,
    "street_name_UPP SERANGOON VIEW": 512,
    "street_name_VEERASAMY RD": 513,
    "street_name_WATERLOO ST": 514,
    "street_name_WELLINGTON CIRCLE": 515,
    "street_name_WEST COAST DR": 516,
    "street_name_WEST COAST RD": 517,
    "street_name_WHAMPOA DR": 518,
    "street_name_WHAMPOA RD": 519,
    "street_name_WHAMPOA STH": 520,
    "street_name_WHAMPOA WEST": 521,
    "street_name_WOODLANDS AVE 1": 522,
    "street_name_WOODLANDS AVE 3": 523,
    "street_name_WOODLANDS AVE 4": 524,
    "street_name_WOODLANDS AVE 5": 525,
    "street_name_WOODLANDS AVE 6": 526,
    "street_name_WOODLANDS AVE 9": 527,
    "street_name_WOODLANDS CIRCLE": 528,
    "street_name_WOODLANDS CRES": 529,
    "street_name_WOODLANDS CTR RD": 530,
    "street_name_WOODLANDS DR 14": 531,
    "street_name_WOODLANDS DR 16": 532,
    "street_name_WOODLANDS DR 40": 533,
    "street_name_WOODLANDS DR 42": 534,
    "street_name_WOODLANDS DR 44": 535,
    "street_name_WOODLANDS DR 50": 536,
    "street_name_WOODLANDS DR 52": 537,
    "street_name_WOODLANDS DR 53": 538,
    "street_name_WOODLANDS DR 60": 539,
    "street_name_WOODLANDS DR 62": 540,
    "street_name_WOODLANDS DR 70": 541,
    "street_name_WOODLANDS DR 71": 542,
    "street_name_WOODLANDS DR 72": 543,
    "street_name_WOODLANDS DR 73": 544,
    "street_name_WOODLANDS DR 75": 545,
    "street_name_WOODLANDS RING RD": 546,
    "street_name_WOODLANDS RISE": 547,
    "street_name_WOODLANDS ST 11": 548,
    "street_name_WOODLANDS ST 13": 549,
    "street_name_WOODLANDS ST 31": 550,
    "street_name_WOODLANDS ST 32": 551,
    "street_name_WOODLANDS ST 41": 552,
    "street_name_WOODLANDS ST 81": 553,
    "street_name_WOODLANDS ST 82": 554,
    "street_name_WOODLANDS ST 83": 555,
    "street_name_YISHUN AVE 1": 556,
    "street_name_YISHUN AVE 11": 557,
    "street_name_YISHUN AVE 2": 558,
    "street_name_YISHUN AVE 3": 559,
    "street_name_YISHUN AVE 4": 560,
    "street_name_YISHUN AVE 5": 561,
    "street_name_YISHUN AVE 6": 562,
    "street_name_YISHUN AVE 7": 563,
    "street_name_YISHUN AVE 9": 564,
    "street_name_YISHUN CTRL": 565,
    "street_name_YISHUN CTRL 1": 566,
    "street_name_YISHUN RING RD": 567,
    "street_name_YISHUN ST 11": 568,
    "street_name_YISHUN ST 20": 569,
    "street_name_YISHUN ST 21": 570,
    "street_name_YISHUN ST 22": 571,
    "street_name_YISHUN ST 31": 572,
    "street_name_YISHUN ST 41": 573,
    "street_name_YISHUN ST 43": 574,
    "street_name_YISHUN ST 51": 575,
    "street_name_YISHUN ST 61": 576,
    "street_name_YISHUN ST 71": 577,
    "street_name_YISHUN ST 72": 578,
    "street_name_YISHUN ST 81": 579,
    "street_name_YUAN CHING RD": 580,
    "street_name_YUNG AN RD": 581,
    "street_name_YUNG HO RD": 582,
    "street_name_YUNG KUANG RD": 583,
    "street_name_YUNG LOH RD": 584,
    "street_name_YUNG PING RD": 585,
    "street_name_YUNG SHENG RD": 586,
    "street_name_ZION RD": 587
}